{"lineId":11108,"name":"花咲線","stations":[{"stationId":1110801,"stationGroupId":1110731},{"stationId":1110802,"stationGroupId":1110802},{"stationId":1110803,"stationGroupId":1110803},{"stationId":1110804,"stationGroupId":1110804},{"stationId":1110805,"stationGroupId":1110805},{"stationId":1110806,"stationGroupId":1110806},{"stationId":1110807,"stationGroupId":1110807},{"stationId":1110808,"stationGroupId":1110808},{"stationId":1110809,"stationGroupId":1110809},{"stationId":1110810,"stationGroupId":1110810},{"stationId":1110811,"stationGroupId":1110811},{"stationId":1110812,"stationGroupId":1110812},{"stationId":1110813,"stationGroupId":1110813},{"stationId":1110814,"stationGroupId":1110814},{"stationId":1110815,"stationGroupId":1110815},{"stationId":1110816,"stationGroupId":1110816},{"stationId":1110817,"stationGroupId":1110817},{"stationId":1110818,"stationGroupId":1110818},{"stationId":1110819,"stationGroupId":1110819},{"stationId":1110820,"stationGroupId":1110820},{"stationId":1110821,"stationGroupId":1110821}]}