{"lineId":11326,"name":"JR京葉線","stations":[{"stationId":1132601,"stationGroupId":1130101},{"stationId":1132602,"stationGroupId":1132602},{"stationId":1132603,"stationGroupId":1132603},{"stationId":1132604,"stationGroupId":1132604},{"stationId":1132605,"stationGroupId":1132605},{"stationId":1132606,"stationGroupId":1132606},{"stationId":1132607,"stationGroupId":1132607},{"stationId":1132608,"stationGroupId":1132608},{"stationId":1132609,"stationGroupId":1132609},{"stationId":1132610,"stationGroupId":1130524},{"stationId":1132611,"stationGroupId":1132611},{"stationId":1132612,"stationGroupId":1132612},{"stationId":1132613,"stationGroupId":1132613},{"stationId":1132614,"stationGroupId":1132614},{"stationId":1132615,"stationGroupId":1132615},{"stationId":1132616,"stationGroupId":1132616},{"stationId":1132617,"stationGroupId":1132617},{"stationId":1132618,"stationGroupId":1132403}]}