{"lineId":23004,"name":"京成千葉線","stations":[{"stationId":2300401,"stationGroupId":2300126},{"stationId":2300402,"stationGroupId":1131334},{"stationId":2300403,"stationGroupId":1131335},{"stationId":2300404,"stationGroupId":2300404},{"stationId":2300405,"stationGroupId":2300405},{"stationId":2300406,"stationGroupId":2300406},{"stationId":2300407,"stationGroupId":2300407},{"stationId":2300408,"stationGroupId":2300408},{"stationId":2300409,"stationGroupId":1131339},{"stationId":2300410,"stationGroupId":2300410}]}